[{"email":"JerryLuu@bcit.ca","pw":"1234","first":"Jerry","last":"Luu"},{"email":"AlexPhan@bcit.ca","pw":"1234","first":"Alex","last":"Phan"},{"email":"mika.ricaplaza@bcit.ca","pw":"1234","first":"Mikhaela","last":"Ricaplaza"},{"email":"YonghanRuan@bcit.ca","pw":"1234","first":"Yonghan","last":"Ruan"},{"email":"JoonyoungKim@bcit.ca","pw":"1234","first":"Joonyoung","last":"Kim"},{"email":"admin@bcit.ca","pw":"1234","first":"Admin","last":"Test"},{"email":"Alexphan1099@gmail.com","pw":"1234","first":"Alex","last":"Phan"},{"email":"Alexphan1099@gmail.com","pw":"1234","first":"Alex","last":"Phan"},{"email":"jaykim@1234.ca","pw":"1234","first":"Jay","last":"Kim"},{"email":"MichaelSanJuan@bcit.ca","pw":"dogs","first":"Steve","last":"Jobs","profilepic":"http://www.attractivepartners.co.uk/wp-content/uploads/2017/06/profile.jpg"}]
